cli/__init__.py
cli/index.py
cli/rsa_encryption.py
pycrypto_tali-0.6.0.dist-info/entry_points.txt
pycrypto_tali-0.6.0.dist-info/METADATA
pycrypto_tali-0.6.0.dist-info/WHEEL
pycrypto_tali-0.6.0.dist-info/RECORD
