Metadata-Version: 2.1
Name: pycrypto-tali
Version: 0.6.0
Summary: CLI Mensajeria encriptada
Author: Kevin Barroso
Author-email: kevin.barroso@taligent.com.ar
Requires-Python: >=3.7,<4.0
Classifier: Programming Language :: Python :: 3
Classifier: Programming Language :: Python :: 3.7
Classifier: Programming Language :: Python :: 3.8
Classifier: Programming Language :: Python :: 3.9
Classifier: Programming Language :: Python :: 3.10
Classifier: Programming Language :: Python :: 3.11
Requires-Dist: cryptography (==39)
Requires-Dist: pyperclip (==1.8.2)
Requires-Dist: typer[all] (>=0.7.0,<0.8.0)
